ami2py/__init__.py
ami2py/amibitstructs.py
ami2py/consts.py
ami2py/revbitinteger.py
ami2py-0.1.0.dist-info/LICENSE
ami2py-0.1.0.dist-info/METADATA
ami2py-0.1.0.dist-info/WHEEL
ami2py-0.1.0.dist-info/top_level.txt
ami2py-0.1.0.dist-info/RECORD
