Metadata-Version: 2.1
Name: ami2py
Version: 0.1.0
Summary: Python Package for reading a amibroker database
Home-page: https://github.com/F2011B/ami2py
Author: Dark Ligt alias FB2011B
License: MIT
Keywords: amibroker database pandas
Platform: UNKNOWN
Classifier: Environment :: Console
Classifier: Environment :: Other Environment
Classifier: Environment :: Web Environment
Classifier: Development Status :: 4 - Beta
Classifier: Intended Audience :: Developers
Classifier: Operating System :: OS Independent
Classifier: Programming Language :: Python :: 3.6
Classifier: Programming Language :: Python :: 3.7
Classifier: Programming Language :: Python :: 3.8
Classifier: Topic :: Software Development :: Libraries :: Python Modules
Requires-Python: >= 3.6
